.gitignore
.hgignore
.hgtags
CREDITS.txt
HISTORY.md
HISTORY.rst
HISTORY.txt
INSTALL.txt
LICENSE.txt
MANIFEST.in
README.rst
buildout.cfg
setup.py
tox.ini
doc/API.html
doc/API.txt
doc/oai.css
doc/oaiclient.py
src/oaipmh/__init__.py
src/oaipmh/client.py
src/oaipmh/common.py
src/oaipmh/datestamp.py
src/oaipmh/error.py
src/oaipmh/interfaces.py
src/oaipmh/metadata.py
src/oaipmh/server.py
src/oaipmh/validation.py
src/oaipmh/tests/OAI-PMH.xsd
src/oaipmh/tests/__init__.py
src/oaipmh/tests/createbrokendata.py
src/oaipmh/tests/createdata.py
src/oaipmh/tests/createdata_deleted_records.py
src/oaipmh/tests/fakeclient.py
src/oaipmh/tests/fakeserver.py
src/oaipmh/tests/runtests.sh
src/oaipmh/tests/test_broken.py
src/oaipmh/tests/test_client.py
src/oaipmh/tests/test_datestamp.py
src/oaipmh/tests/test_deleted_records.py
src/oaipmh/tests/test_server.py
src/oaipmh/tests/test_validation.py
src/oaipmh/tests/fake1/00000.xml
src/oaipmh/tests/fake1/00001.xml
src/oaipmh/tests/fake1/00002.xml
src/oaipmh/tests/fake1/00003.xml
src/oaipmh/tests/fake1/00004.xml
src/oaipmh/tests/fake1/00005.xml
src/oaipmh/tests/fake1/00006.xml
src/oaipmh/tests/fake1/mapping.txt
src/oaipmh/tests/fake2/00000.xml
src/oaipmh/tests/fake2/00001.xml
src/oaipmh/tests/fake2/00002.xml
src/oaipmh/tests/fake2/mapping.txt
src/oaipmh/tests/fake3/00001.xml
src/oaipmh/tests/fake3/mapping.txt
src/oaipmh/tests/fake4/00001.xml
src/oaipmh/tests/fake4/mapping.txt
src/oaipmh/tests/fake5/00001.xml
src/oaipmh/tests/fake5/mapping.txt
src/pyoai.egg-info/PKG-INFO
src/pyoai.egg-info/SOURCES.txt
src/pyoai.egg-info/dependency_links.txt
src/pyoai.egg-info/not-zip-safe
src/pyoai.egg-info/requires.txt
src/pyoai.egg-info/top_level.txt