Metadata-Version: 2.1
Name: pyoai
Version: 2.5.1
Summary: The oaipmh module is a Python implementation of an "Open Archives Initiative Protocol for Metadata Harvesting" (version 2) client and server.
Home-page: http://www.infrae.com/download/oaipmh
Author: Infrae
Author-email: info@infrae.com
License: BSD
Keywords: OAI-PMH xml archive
Platform: UNKNOWN
Classifier: Development Status :: 4 - Beta
Classifier: Programming Language :: Python
Classifier: License :: OSI Approved :: BSD License
Classifier: Topic :: Software Development :: Libraries :: Python Modules
Classifier: Environment :: Web Environment
